Workbook

Sheet Orders
A1: Row ID | B1: Order ID | C1: Order Date | D1: Ship Date | E1: Ship Mode | F1: Customer ID | G1: Customer Name | H1: Segment | I1: Country/Region | J1: City | K1: State | L1: Postal Code | M1: Region | N1: Sales Manager | O1: Product ID | P1: Category | Q1: Sub-Category | R1: Product Name | S1: Sales | T1: Quantity | U1: Discount | V1: Profit
A2: 1 | B2: CA-2018-152156 | C2: 43412 | D2: 43415 | E2: Second Class | F2: CG-12520 | G2: Claire Gute | H2: Consumer | I2: United States | J2: Henderson | K2: Kentucky | L2: 42420 | M2: South | N2: =VLOOKUP(M2,People!$A$1:$C$5,2,0) -> Cassandra Brandow | O2: FUR-BO-10001798 | P2: Furniture | Q2: Bookcases | R2: Bush Somerset Collection Bookcase | S2: 261.96 | T2: 2 | U2: 0 | V2: 41.9136
A3: 2 | B3: CA-2018-152156 | C3: 43412 | D3: 43415 | E3: Second Class | F3: CG-12520 | G3: Claire Gute | H3: Consumer | I3: United States | J3: Henderson | K3: Kentucky | L3: 42420 | M3: South | N3: =VLOOKUP(M3,People!$A$1:$C$5,2,0) -> Cassandra Brandow | O3: FUR-CH-10000454 | P3: Furniture | Q3: Chairs | R3: Hon Deluxe Fabric Upholstered Stacking Chairs, Rounded Back | S3: 731.94 | T3: 3 | U3: 0 | V3: 219.582 | Z3: =SUMIFS(V:V,P:P,"Furniture",M:M,"South") -> 6771.2061
A4: 3 | B4: CA-2018-138688 | C4: 43263 | D4: 43267 | E4: Second Class | F4: DV-13045 | G4: Darrin Van Huff | H4: Corporate | I4: United States | J4: Los Angeles | K4: California | L4: 90036 | M4: West | N4: =VLOOKUP(M4,People!$A$1:$C$5,2,0) -> Anna Andreadi | O4: OFF-LA-10000240 | P4: Office Supplies | Q4: Labels | R4: Self-Adhesive Address Labels for Typewriters by Universal | S4: 14.62 | T4: 2 | U4: 0 | V4: 6.8714
A5: 4 | B5: US-2017-108966 | C5: 43019 | D5: 43026 | E5: Standard Class | F5: SO-20335 | G5: Sean O'Donnell | H5: Consumer | I5: United States | J5: Fort Lauderdale | K5: Florida | L5: 33311 | M5: South | N5: =VLOOKUP(M5,People!$A$1:$C$5,2,0) -> Cassandra Brandow | O5: FUR-TA-10000577 | P5: Furniture | Q5: Tables | R5: Bretford CR4500 Series Slim Rectangular Table | S5: 957.5775 | T5: 5 | U5: 0.45 | V5: -383.031 | Z5: =AVERAGEIFS(U:U,P:P,"Furniture",M:M, "South") -> 0.12153614
A6: 5 | B6: US-2017-108966 | C6: 43019 | D6: 43026 | E6: Standard Class | F6: SO-20335 | G6: Sean O'Donnell | H6: Consumer | I6: United States | J6: Fort Lauderdale | K6: Florida | L6: 33311 | M6: South | N6: =VLOOKUP(M6,People!$A$1:$C$5,2,0) -> Cassandra Brandow | O6: OFF-ST-10000760 | P6: Office Supplies | Q6: Storage | R6: Eldon Fold 'N Roll Cart System | S6: 22.368 | T6: 2 | U6: 0.2 | V6: 2.5164
A7: 6 | B7: CA-2016-115812 | C7: 42530 | D7: 42535 | E7: Standard Class | F7: BH-11710 | G7: Brosina Hoffman | H7: Consumer | I7: United States | J7: Los Angeles | K7: California | L7: 90032 | M7: West | N7: =VLOOKUP(M7,People!$A$1:$C$5,2,0) -> Anna Andreadi | O7: FUR-FU-10001487 | P7: Furniture | Q7: Furnishings | R7: Eldon Expressions Wood and Plastic Desk Accessories, Cherry Wood | S7: 48.86 | T7: 7 | U7: 0 | V7: 14.1694
A8: 7 | B8: CA-2016-115812 | C8: 42530 | D8: 42535 | E8: Standard Class | F8: BH-11710 | G8: Brosina Hoffman | H8: Consumer | I8: United States | J8: Los Angeles | K8: California | L8: 90032 | M8: West | N8: =VLOOKUP(M8,People!$A$1:$C$5,2,0) -> Anna Andreadi | O8: OFF-AR-10002833 | P8: Office Supplies | Q8: Art | R8: Newell 322 | S8: 7.28 | T8: 4 | U8: 0 | V8: 1.9656
A9: 8 | B9: CA-2016-115812 | C9: 42530 | D9: 42535 | E9: Standard Class | F9: BH-11710 | G9: Brosina Hoffman | H9: Consumer | I9: United States | J9: Los Angeles | K9: California | L9: 90032 | M9: West | N9: =VLOOKUP(M9,People!$A$1:$C$5,2,0) -> Anna Andreadi | O9: TEC-PH-10002275 | P9: Technology | Q9: Phones | R9: Mitel 5320 IP Phone VoIP phone | S9: 907.152 | T9: 6 | U9: 0.2 | V9: 90.7152
A10: 9 | B10: CA-2016-115812 | C10: 42530 | D10: 42535 | E10: Standard Class | F10: BH-11710 | G10: Brosina Hoffman | H10: Consumer | I10: United States | J10: Los Angeles | K10: California | L10: 90032 | M10: West | N10: =VLOOKUP(M10,People!$A$1:$C$5,2,0) -> Anna Andreadi | O10: OFF-BI-10003910 | P10: Office Supplies | Q10: Binders | R10: DXL Angle-View Binders with Locking Rings by Samsill | S10: 18.504 | T10: 3 | U10: 0.2 | V10: 5.7825
A11: 10 | B11: CA-2016-115812 | C11: 42530 | D11: 42535 | E11: Standard Class | F11: BH-11710 | G11: Brosina Hoffman | H11: Consumer | I11: United States | J11: Los Angeles | K11: California | L11: 90032 | M11: West | N11: =VLOOKUP(M11,People!$A$1:$C$5,2,0) -> Anna Andreadi | O11: OFF-AP-10002892 | P11: Office Supplies | Q11: Appliances | R11: Belkin F5C206VTEL 6 Outlet Surge | S11: 114.9 | T11: 5 | U11: 0 | V11: 34.47
A12: 11 | B12: CA-2016-115812 | C12: 42530 | D12: 42535 | E12: Standard Class | F12: BH-11710 | G12: Brosina Hoffman | H12: Consumer | I12: United States | J12: Los Angeles | K12: California | L12: 90032 | M12: West | N12: =VLOOKUP(M12,People!$A$1:$C$5,2,0) -> Anna Andreadi | O12: FUR-TA-10001539 | P12: Furniture | Q12: Tables | R12: Chromcraft Rectangular Conference Tables | S12: 1706.184 | T12: 9 | U12: 0.2 | V12: 85.3092
A13: 12 | B13: CA-2016-115812 | C13: 42530 | D13: 42535 | E13: Standard Class | F13: BH-11710 | G13: Brosina Hoffman | H13: Consumer | I13: United States | J13: Los Angeles | K13: California | L13: 90032 | M13: West | N13: =VLOOKUP(M13,People!$A$1:$C$5,2,0) -> Anna Andreadi | O13: TEC-PH-10002033 | P13: Technology | Q13: Phones | R13: Konftel 250 Conference phone - Charcoal black | S13: 911.424 | T13: 4 | U13: 0.2 | V13: 68.3568
A14: 13 | B14: CA-2019-114412 | C14: 43570 | D14: 43575 | E14: Standard Class | F14: AA-10480 | G14: Andrew Allen | H14: Consumer | I14: United States | J14: Concord | K14: North Carolina | L14: 28027 | M14: South | N14: =VLOOKUP(M14,People!$A$1:$C$5,2,0) -> Cassandra Brandow | O14: OFF-PA-10002365 | P14: Office Supplies | Q14: Paper | R14: Xerox 1967 | S14: 15.552 | T14: 3 | U14: 0.2 | V14: 5.4432
A15: 14 | B15: CA-2018-161389 | C15: 43439 | D15: 43444 | E15: Standard Class | F15: IM-15070 | G15: Irene Maddox | H15: Consumer | I15: United States | J15: Seattle | K15: Washington | L15: 98103 | M15: West | N15: =VLOOKUP(M15,People!$A$1:$C$5,2,0) -> Anna Andreadi | O15: OFF-BI-10003656 | P15: Office Supplies | Q15: Binders | R15: Fellowes PB200 Plastic Comb Binding Machine | S15: 407.976 | T15: 3 | U15: 0.2 | V15: 132.5922
A16: 15 | B16: US-2017-118983 | C16: 43061 | D16: 43065 | E16: Standard Class | F16: HP-14815 | G16: Harold Pawlan | H16: Home Office | I16: United States | J16: Fort Worth | K16: Texas | L16: 76106 | M16: Central | N16: =VLOOKUP(M16,People!$A$1:$C$5,2,0) -> Kelly Williams | O16: OFF-AP-10002311 | P16: Office Supplies | Q16: Appliances | R16: Holmes Replacement Filter for HEPA Air Cleaner, Very Large Room, HEPA Filter | S16: 68.81 | T16: 5 | U16: 0.8 | V16: -123.858
A17: 16 | B17: US-2017-118983 | C17: 43061 | D17: 43065 | E17: Standard Class | F17: HP-14815 | G17: Harold Pawlan | H17: Home Office | I17: United States | J17: Fort Worth | K17: Texas | L17: 76106 | M17: Central | N17: =VLOOKUP(M17,People!$A$1:$C$5,2,0) -> Kelly Williams | O17: OFF-BI-10000756 | P17: Office Supplies | Q17: Binders | R17: Storex DuraTech Recycled Plastic Frosted Binders | S17: 2.544 | T17: 3 | U17: 0.8 | V17: -3.816
... A2235: 2234 | B2235: CA-2017-123232 | C2235: 43083 | D2235: 43085 | E2235: Second Class | F2235: DJ-13630 | G2235: Doug Jacobs | H2235: Consumer | I2235: United States | J2235: Portland | K2235: Oregon | L2235: 97206 | M2235: West | N2235: =VLOOKUP(M2235,People!$A$1:$C$5,2,0) -> Anna Andreadi | O2235: TEC-PH-10001051 | P2235: Technology | Q2235: Phones | R2235: HTC One | S2235: 319.968 | T2235: 4 | U2235: 0.2 | V2235: 35.9964
A2236: 2235 | B2236: CA-2019-104066 | C2236: 43804 | D2236: 43809 | E2236: Standard Class | F2236: QJ-19255 | G2236: Quincy Jones | H2236: Corporate | I2236: United States | J2236: Burlington | K2236: Vermont | M2236: East | N2236: =VLOOKUP(M2236,People!$A$1:$C$5,2,0) -> Chuck Magee | O2236: TEC-AC-10001013 | P2236: Technology | Q2236: Accessories | R2236: Logitech ClearChat Comfort/USB Headset H390 | S2236: 205.03 | T2236: 7 | U2236: 0 | V2236: 67.6599
A2237: 2236 | B2237: CA-2017-145849 | C2237: 42993 | D2237: 42995 | E2237: Second Class | F2237: CT-11995 | G2237: Carol Triggs | H2237: Consumer | I2237: United States | J2237: Indianapolis | K2237: Indiana | L2237: 46203 | M2237: Central | N2237: =VLOOKUP(M2237,People!$A$1:$C$5,2,0) -> Kelly Williams | O2237: OFF-ST-10000025 | P2237: Office Supplies | Q2237: Storage | R2237: Fellowes Stor/Drawer Steel Plus Storage Drawers | S2237: 190.86 | T2237: 2 | U2237: 0 | V2237: 11.4516
A2238: 2237 | B2238: CA-2017-145849 | C2238: 42993 | D2238: 42995 | E2238: Second Class | F2238: CT-11995 | G2238: Carol Triggs | H2238: Consumer | I2238: United States | J2238: Indianapolis | K2238: Indiana | L2238: 46203 | M2238: Central | N2238: =VLOOKUP(M2238,People!$A$1:$C$5,2,0) -> Kelly Williams | O2238: OFF-AR-10000817 | P2238: Office Supplies | Q2238: Art | R2238: Manco Dry-Lighter Erasable Highlighter | S2238: 24.32 | T2238: 8 | U2238: 0 | V2238: 8.2688
A2239: 2238 | B2239: CA-2018-122322 | C2239: 43296 | D2239: 43302 | E2239: Standard Class | F2239: RH-19510 | G2239: Rick Huthwaite | H2239: Home Office | I2239: United States | J2239: Provo | K2239: Utah | L2239: 84604 | M2239: West | N2239: =VLOOKUP(M2239,People!$A$1:$C$5,2,0) -> Anna Andreadi | O2239: OFF-SU-10000952 | P2239: Office Supplies | Q2239: Supplies | R2239: Fiskars Home & Office Scissors | S2239: 44.4 | T2239: 5 | U2239: 0 | V2239: 12.432
A2240: 2239 | B2240: CA-2019-166849 | C2240: 43575 | D2240: 43581 | E2240: Standard Class | F2240: SJ-20125 | G2240: Sanjit Jacobs | H2240: Home Office | I2240: United States | J2240: Chicago | K2240: Illinois | L2240: 60610 | M2240: Central | N2240: =VLOOKUP(M2240,People!$A$1:$C$5,2,0) -> Kelly Williams | O2240: FUR-FU-10004597 | P2240: Furniture | Q2240: Furnishings | R2240: Eldon Cleatmat Chair Mats for Medium Pile Carpets | S2240: 44.4 | T2240: 2 | U2240: 0.6 | V2240: -52.17
A2241: 2240 | B2241: CA-2018-146633 | C2241: 43419 | D2241: 43421 | E2241: Second Class | F2241: TG-21310 | G2241: Toby Gnade | H2241: Consumer | I2241: United States | J2241: Los Angeles | K2241: California | L2241: 90049 | M2241: West | N2241: =VLOOKUP(M2241,People!$A$1:$C$5,2,0) -> Anna Andreadi | O2241: OFF-BI-10003527 | P2241: Office Supplies | Q2241: Binders | R2241: Fellowes PB500 Electric Punch Plastic Comb Binding Machine with Manual Bind | S2241: 1016.792 | T2241: 1 | U2241: 0.2 | V2241: 381.297
A2242: 2241 | B2242: CA-2018-146633 | C2242: 43419 | D2242: 43421 | E2242: Second Class | F2242: TG-21310 | G2242: Toby Gnade | H2242: Consumer | I2242: United States | J2242: Los Angeles | K2242: California | L2242: 90049 | M2242: West | N2242: =VLOOKUP(M2242,People!$A$1:$C$5,2,0) -> Anna Andreadi | O2242: OFF-BI-10002982 | P2242: Office Supplies | Q2242: Binders | R2242: Avery Self-Adhesive Photo Pockets for Polaroid Photos | S2242: 38.136 | T2242: 7 | U2242: 0.2 | V2242: 13.3476
A2243: 2242 | B2243: US-2018-126893 | C2243: 43430 | D2243: 43435 | E2243: Standard Class | F2243: CT-11995 | G2243: Carol Triggs | H2243: Consumer | I2243: United States | J2243: Philadelphia | K2243: Pennsylvania | L2243: 19134 | M2243: East | N2243: =VLOOKUP(M2243,People!$A$1:$C$5,2,0) -> Chuck Magee | O2243: TEC-PH-10004165 | P2243: Technology | Q2243: Phones | R2243: Mitel MiVoice 5330e IP Phone | S2243: 494.982 | T2243: 3 | U2243: 0.4 | V2243: -115.4958
A2244: 2243 | B2244: CA-2019-103380 | C2244: 43790 | D2244: 43794 | E2244: Standard Class | F2244: BF-11005 | G2244: Barry Franz | H2244: Home Office | I2244: United States | J2244: Pasadena | K2244: California | L2244: 91104 | M2244: West | N2244: =VLOOKUP(M2244,People!$A$1:$C$5,2,0) -> Anna Andreadi | O2244: OFF-ST-10003442 | P2244: Office Supplies | Q2244: Storage | R2244: Eldon Portable Mobile Manager | S2244: 56.56 | T2244: 2 | U2244: 0 | V2244: 15.2712
A2245: 2244 | B2245: CA-2019-103380 | C2245: 43790 | D2245: 43794 | E2245: Standard Class | F2245: BF-11005 | G2245: Barry Franz | H2245: Home Office | I2245: United States | J2245: Pasadena | K2245: California | L2245: 91104 | M2245: West | N2245: =VLOOKUP(M2245,People!$A$1:$C$5,2,0) -> Anna Andreadi | O2245: OFF-AR-10003856 | P2245: Office Supplies | Q2245: Art | R2245: Newell 344 | S2245: 5.56 | T2245: 2 | U2245: 0 | V2245: 1.4456
A2246: 2245 | B2246: CA-2019-103380 | C2246: 43790 | D2246: 43794 | E2246: Standard Class | F2246: BF-11005 | G2246: Barry Franz | H2246: Home Office | I2246: United States | J2246: Pasadena | K2246: California | L2246: 91104 | M2246: West | N2246: =VLOOKUP(M2246,People!$A$1:$C$5,2,0) -> Anna Andreadi | O2246: OFF-FA-10004248 | P2246: Office Supplies | Q2246: Fasteners | R2246: Advantus T-Pin Paper Clips | S2246: 9.02 | T2246: 2 | U2246: 0 | V2246: 3.5178
A2247: 2246 | B2247: CA-2019-103380 | C2247: 43790 | D2247: 43794 | E2247: Standard Class | F2247: BF-11005 | G2247: Barry Franz | H2247: Home Office | I2247: United States | J2247: Pasadena | K2247: California | L2247: 91104 | M2247: West | N2247: =VLOOKUP(M2247,People!$A$1:$C$5,2,0) -> Anna Andreadi | O2247: OFF-AP-10001492 | P2247: Office Supplies | Q2247: Appliances | R2247: Acco Six-Outlet Power Strip, 4' Cord Length | S2247: 8.62 | T2247: 1 | U2247: 0 | V2247: 2.2412
A2248: 2247 | B2248: CA-2019-103380 | C2248: 43790 | D2248: 43794 | E2248: Standard Class | F2248: BF-11005 | G2248: Barry Franz | H2248: Home Office | I2248: United States | J2248: Pasadena | K2248: California | L2248: 91104 | M2248: West | N2248: =VLOOKUP(M2248,People!$A$1:$C$5,2,0) -> Anna Andreadi | O2248: TEC-PH-10004165 | P2248: Technology | Q2248: Phones | R2248: Mitel MiVoice 5330e IP Phone | S2248: 659.976 | T2248: 3 | U2248: 0.2 | V2248: 49.4982
... A5275: 5274 | B5275: US-2018-158309 | C5275: 43430 | D5275: 43433 | E5275: First Class | F5275: PA-19060 | G5275: Pete Armstrong | H5275: Home Office | I5275: United States | J5275: Miami | K5275: Florida | L5275: 33142 | M5275: South | N5275: =VLOOKUP(M5275,People!$A$1:$C$5,2,0) -> Cassandra Brandow | O5275: OFF-BI-10000145 | P5275: Office Supplies | Q5275: Binders | R5275: Zipper Ring Binder Pockets | S5275: 3.744 | T5275: 4 | U5275: 0.7 | V5275: -2.6208
A5276: 5275 | B5276: CA-2017-162887 | C5276: 43046 | D5276: 43048 | E5276: Second Class | F5276: SV-20785 | G5276: Stewart Visinsky | H5276: Consumer | I5276: United States | J5276: Burlington | K5276: Vermont | M5276: East | N5276: =VLOOKUP(M5276,People!$A$1:$C$5,2,0) -> Chuck Magee | O5276: FUR-CH-10000595 | P5276: Furniture | Q5276: Chairs | R5276: Safco Contoured Stacking Chairs | S5276: 715.2 | T5276: 3 | U5276: 0 | V5276: 178.8
A5277: 5276 | B5277: CA-2019-147333 | C5277: 43813 | D5277: 43819 | E5277: Standard Class | F5277: KL-16555 | G5277: Kelly Lampkin | H5277: Corporate | I5277: United States | J5277: Fayetteville | K5277: Arkansas | L5277: 72701 | M5277: South | N5277: =VLOOKUP(M5277,People!$A$1:$C$5,2,0) -> Cassandra Brandow | O5277: TEC-AC-10004469 | P5277: Technology | Q5277: Accessories | R5277: Microsoft Sculpt Comfort Mouse | S5277: 159.8 | T5277: 4 | U5277: 0 | V5277: 70.312
A5278: 5277 | B5278: CA-2019-147333 | C5278: 43813 | D5278: 43819 | E5278: Standard Class | F5278: KL-16555 | G5278: Kelly Lampkin | H5278: Corporate | I5278: United States | J5278: Fayetteville | K5278: Arkansas | L5278: 72701 | M5278: South | N5278: =VLOOKUP(M5278,People!$A$1:$C$5,2,0) -> Cassandra Brandow | O5278: TEC-AC-10003038 | P5278: Technology | Q5278: Accessories | R5278: Kingston Digital DataTraveler 16GB USB 2.0 | S5278: 44.75 | T5278: 5 | U5278: 0 | V5278: 8.5025
A5279: 5278 | B5279: CA-2016-113859 | C5279: 42626 | D5279: 42630 | E5279: Standard Class | F5279: BC-11125 | G5279: Becky Castell | H5279: Home Office | I5279: United States | J5279: Odessa | K5279: Texas | L5279: 79762 | M5279: Central | N5279: =VLOOKUP(M5279,People!$A$1:$C$5,2,0) -> Kelly Williams | O5279: FUR-CH-10004698 | P5279: Furniture | Q5279: Chairs | R5279: Padded Folding Chairs, Black, 4/Carton | S5279: 340.116 | T5279: 6 | U5279: 0.3 | V5279: -9.7176
A5280: 5279 | B5280: CA-2016-159681 | C5280: 42711 | D5280: 42717 | E5280: Standard Class | F5280: PO-18850 | G5280: Patrick O'Brill | H5280: Consumer | I5280: United States | J5280: Virginia Beach | K5280: Virginia | L5280: 23464 | M5280: South | N5280: =VLOOKUP(M5280,People!$A$1:$C$5,2,0) -> Cassandra Brandow | O5280: OFF-PA-10003641 | P5280: Office Supplies | Q5280: Paper | R5280: Xerox 1909 | S5280: 105.52 | T5280: 4 | U5280: 0 | V5280: 48.5392
A5281: 5280 | B5281: US-2019-104094 | C5281: 43715 | D5281: 43719 | E5281: Standard Class | F5281: AG-10675 | G5281: Anna Gayman | H5281: Consumer | I5281: United States | J5281: Milwaukee | K5281: Wisconsin | L5281: 53209 | M5281: Central | N5281: =VLOOKUP(M5281,People!$A$1:$C$5,2,0) -> Kelly Williams | O5281: TEC-AC-10002134 | P5281: Technology | Q5281: Accessories | R5281: Rosewill 107 Normal Keys USB Wired Standard Keyboard | S5281: 13.48 | T5281: 1 | U5281: 0 | V5281: 1.8872
A5282: 5281 | B5282: CA-2019-152709 | C5282: 43745 | D5282: 43750 | E5282: Standard Class | F5282: DB-13210 | G5282: Dean Braden | H5282: Consumer | I5282: United States | J5282: Detroit | K5282: Michigan | L5282: 48234 | M5282: Central | N5282: =VLOOKUP(M5282,People!$A$1:$C$5,2,0) -> Kelly Williams | O5282: OFF-ST-10001837 | P5282: Office Supplies | Q5282: Storage | R5282: SAFCO Mobile Desk Side File, Wire Frame | S5282: 85.52 | T5282: 2 | U5282: 0 | V5282: 22.2352
A5283: 5282 | B5283: CA-2017-105158 | C5283: 42983 | D5283: 42988 | E5283: Standard Class | F5283: SP-20860 | G5283: Sung Pak | H5283: Corporate | I5283: United States | J5283: Rochester | K5283: Minnesota | L5283: 55901 | M5283: Central | N5283: =VLOOKUP(M5283,People!$A$1:$C$5,2,0) -> Kelly Williams | O5283: FUR-FU-10001706 | P5283: Furniture | Q5283: Furnishings | R5283: Longer-Life Soft White Bulbs | S5283: 6.16 | T5283: 2 | U5283: 0 | V5283: 2.9568
A5284: 5283 | B5284: CA-2017-105158 | C5284: 42983 | D5284: 42988 | E5284: Standard Class | F5284: SP-20860 | G5284: Sung Pak | H5284: Corporate | I5284: United States | J5284: Rochester | K5284: Minnesota | L5284: 55901 | M5284: Central | N5284: =VLOOKUP(M5284,People!$A$1:$C$5,2,0) -> Kelly Williams | O5284: OFF-PA-10001970 | P5284: Office Supplies | Q5284: Paper | R5284: Xerox 1881 | S5284: 36.84 | T5284: 3 | U5284: 0 | V5284: 17.3148
A5285: 5284 | B5285: CA-2016-133424 | C5285: 42459 | D5285: 42464 | E5285: Standard Class | F5285: Dl-13600 | G5285: Dorris liebe | H5285: Corporate | I5285: United States | J5285: Seattle | K5285: Washington | L5285: 98105 | M5285: West | N5285: =VLOOKUP(M5285,People!$A$1:$C$5,2,0) -> Anna Andreadi | O5285: OFF-ST-10002957 | P5285: Office Supplies | Q5285: Storage | R5285: Sterilite Show Offs Storage Containers | S5285: 15.84 | T5285: 3 | U5285: 0 | V5285: 0
A5286: 5285 | B5286: CA-2016-133424 | C5286: 42459 | D5286: 42464 | E5286: Standard Class | F5286: Dl-13600 | G5286: Dorris liebe | H5286: Corporate | I5286: United States | J5286: Seattle | K5286: Washington | L5286: 98105 | M5286: West | N5286: =VLOOKUP(M5286,People!$A$1:$C$5,2,0) -> Anna Andreadi | O5286: OFF-LA-10002312 | P5286: Office Supplies | Q5286: Labels | R5286: Avery 490 | S5286: 44.4 | T5286: 3 | U5286: 0 | V5286: 22.2
A5287: 5286 | B5287: CA-2019-105991 | C5287: 43590 | D5287: 43591 | E5287: First Class | F5287: LH-17020 | G5287: Lisa Hazard | H5287: Consumer | I5287: United States | J5287: Louisville | K5287: Colorado | L5287: 80027 | M5287: West | N5287: =VLOOKUP(M5287,People!$A$1:$C$5,2,0) -> Anna Andreadi | O5287: OFF-EN-10002600 | P5287: Office Supplies | Q5287: Envelopes | R5287: Redi-Strip #10 Envelopes, 4 1/8 x 9 1/2 | S5287: 21.24 | T5287: 9 | U5287: 0.2 | V5287: 7.434
A5288: 5287 | B5288: CA-2019-105991 | C5288: 43590 | D5288: 43591 | E5288: First Class | F5288: LH-17020 | G5288: Lisa Hazard | H5288: Consumer | I5288: United States | J5288: Louisville | K5288: Colorado | L5288: 80027 | M5288: West | N5288: =VLOOKUP(M5288,People!$A$1:$C$5,2,0) -> Anna Andreadi | O5288: OFF-BI-10003274 | P5288: Office Supplies | Q5288: Binders | R5288: Avery Durable Slant Ring Binders, No Labels | S5288: 9.552 | T5288: 8 | U5288: 0.7 | V5288: -7.3232
... A8799: 8798 | B8799: CA-2018-106397 | C8799: 43288 | D8799: 43294 | E8799: Standard Class | F8799: MJ-17740 | G8799: Max Jones | H8799: Consumer | I8799: United States | J8799: Orem | K8799: Utah | L8799: 84057 | M8799: West | N8799: =VLOOKUP(M8799,People!$A$1:$C$5,2,0) -> Anna Andreadi | O8799: OFF-AR-10004602 | P8799: Office Supplies | Q8799: Art | R8799: Boston KS Multi-Size Manual Pencil Sharpener | S8799: 45.98 | T8799: 2 | U8799: 0 | V8799: 12.8744
A8800: 8799 | B8800: US-2018-150140 | C8800: 43196 | D8800: 43200 | E8800: Standard Class | F8800: VM-21685 | G8800: Valerie Mitchum | H8800: Home Office | I8800: United States | J8800: Burlington | K8800: Vermont | M8800: East | N8800: =VLOOKUP(M8800,People!$A$1:$C$5,2,0) -> Chuck Magee | O8800: TEC-PH-10002555 | P8800: Technology | Q8800: Phones | R8800: Nortel Meridian M5316 Digital phone | S8800: 1294.75 | T8800: 5 | U8800: 0 | V8800: 336.635
A8801: 8800 | B8801: CA-2016-116666 | C8801: 42498 | D8801: 42500 | E8801: First Class | F8801: KT-16480 | G8801: Kean Thornton | H8801: Consumer | I8801: United States | J8801: Philadelphia | K8801: Pennsylvania | L8801: 19134 | M8801: East | N8801: =VLOOKUP(M8801,People!$A$1:$C$5,2,0) -> Chuck Magee | O8801: TEC-CO-10001449 | P8801: Technology | Q8801: Copiers | R8801: Hewlett Packard LaserJet 3310 Copier | S8801: 1799.97 | T8801: 5 | U8801: 0.4 | V8801: 239.996
A8802: 8801 | B8802: CA-2019-148992 | C8802: 43792 | D8802: 43796 | E8802: Standard Class | F8802: CS-12250 | G8802: Chris Selesnick | H8802: Corporate | I8802: United States | J8802: Chicago | K8802: Illinois | L8802: 60623 | M8802: Central | N8802: =VLOOKUP(M8802,People!$A$1:$C$5,2,0) -> Kelly Williams | O8802: OFF-PA-10004285 | P8802: Office Supplies | Q8802: Paper | R8802: Xerox 1959 | S8802: 10.688 | T8802: 2 | U8802: 0.2 | V8802: 3.7408
A8803: 8802 | B8803: CA-2018-140935 | C8803: 43414 | D8803: 43416 | E8803: First Class | F8803: AB-10015 | G8803: Aaron Bergman | H8803: Consumer | I8803: United States | J8803: Oklahoma City | K8803: Oklahoma | L8803: 73120 | M8803: Central | N8803: =VLOOKUP(M8803,People!$A$1:$C$5,2,0) -> Kelly Williams | O8803: TEC-PH-10000562 | P8803: Technology | Q8803: Phones | R8803: Samsung Convoy 3 | S8803: 221.98 | T8803: 2 | U8803: 0 | V8803: 62.1544
A8804: 8803 | B8804: CA-2018-140935 | C8804: 43414 | D8804: 43416 | E8804: First Class | F8804: AB-10015 | G8804: Aaron Bergman | H8804: Consumer | I8804: United States | J8804: Oklahoma City | K8804: Oklahoma | L8804: 73120 | M8804: Central | N8804: =VLOOKUP(M8804,People!$A$1:$C$5,2,0) -> Kelly Williams | O8804: FUR-BO-10003966 | P8804: Furniture | Q8804: Bookcases | R8804: Sauder Facets Collection Library, Sky Alder Finish | S8804: 341.96 | T8804: 2 | U8804: 0 | V8804: 54.7136
A8805: 8804 | B8805: CA-2016-157644 | C8805: 42735 | D8805: 42736 | E8805: First Class | F8805: AH-10030 | G8805: Aaron Hawkins | H8805: Corporate | I8805: United States | J8805: New York City | K8805: New York | L8805: 10035 | M8805: East | N8805: =VLOOKUP(M8805,People!$A$1:$C$5,2,0) -> Chuck Magee | O8805: TEC-AC-10003614 | P8805: Technology | Q8805: Accessories | R8805: Verbatim 25 GB 6x Blu-ray Single Layer Recordable Disc, 10/Pack | S8805: 34.77 | T8805: 3 | U8805: 0 | V8805: 11.4741
A8806: 8805 | B8806: CA-2016-157644 | C8806: 42735 | D8806: 42736 | E8806: First Class | F8806: AH-10030 | G8806: Aaron Hawkins | H8806: Corporate | I8806: United States | J8806: New York City | K8806: New York | L8806: 10035 | M8806: East | N8806: =VLOOKUP(M8806,People!$A$1:$C$5,2,0) -> Chuck Magee | O8806: OFF-LA-10003148 | P8806: Office Supplies | Q8806: Labels | R8806: Avery 51 | S8806: 18.9 | T8806: 3 | U8806: 0 | V8806: 8.694
A8807: 8806 | B8807: US-2019-100398 | C8807: 43696 | D8807: 43700 | E8807: Standard Class | F8807: DO-13435 | G8807: Denny Ordway | H8807: Consumer | I8807: United States | J8807: Salt Lake City | K8807: Utah | L8807: 84106 | M8807: West | N8807: =VLOOKUP(M8807,People!$A$1:$C$5,2,0) -> Anna Andreadi | O8807: OFF-BI-10002133 | P8807: Office Supplies | Q8807: Binders | R8807: Wilson Jones Elliptical Ring 3 1/2" Capacity Binders, 800 sheets | S8807: 102.72 | T8807: 3 | U8807: 0.2 | V8807: 37.236
A8808: 8807 | B8808: CA-2018-113082 | C8808: 43355 | D8808: 43359 | E8808: Standard Class | F8808: MC-17590 | G8808: Matt Collister | H8808: Corporate | I8808: United States | J8808: Utica | K8808: New York | L8808: 13501 | M8808: East | N8808: =VLOOKUP(M8808,People!$A$1:$C$5,2,0) -> Chuck Magee | O8808: FUR-FU-10002813 | P8808: Furniture | Q8808: Furnishings | R8808: DAX Contemporary Wood Frame with Silver Metal Mat, Desktop, 11 x 14 Size | S8808: 40.48 | T8808: 2 | U8808: 0 | V8808: 14.5728
A8809: 8808 | B8809: US-2019-110646 | C8809: 43764 | D8809: 43769 | E8809: Standard Class | F8809: JF-15190 | G8809: Jamie Frazer | H8809: Consumer | I8809: United States | J8809: Philadelphia | K8809: Pennsylvania | L8809: 19134 | M8809: East | N8809: =VLOOKUP(M8809,People!$A$1:$C$5,2,0) -> Chuck Magee | O8809: OFF-BI-10004330 | P8809: Office Supplies | Q8809: Binders | R8809: GBC Velobind Prepunched Cover Sets, Regency Series | S8809: 33.282 | T8809: 3 | U8809: 0.7 | V8809: -27.735
A8810: 8809 | B8810: US-2019-110646 | C8810: 43764 | D8810: 43769 | E8810: Standard Class | F8810: JF-15190 | G8810: Jamie Frazer | H8810: Consumer | I8810: United States | J8810: Philadelphia | K8810: Pennsylvania | L8810: 19134 | M8810: East | N8810: =VLOOKUP(M8810,People!$A$1:$C$5,2,0) -> Chuck Magee | O8810: TEC-PH-10002807 | P8810: Technology | Q8810: Phones | R8810: Motorla HX550 Universal Bluetooth Headset | S8810: 118.65 | T8810: 5 | U8810: 0.4 | V8810: 19.775
A8811: 8810 | B8811: US-2019-110646 | C8811: 43764 | D8811: 43769 | E8811: Standard Class | F8811: JF-15190 | G8811: Jamie Frazer | H8811: Consumer | I8811: United States | J8811: Philadelphia | K8811: Pennsylvania | L8811: 19134 | M8811: East | N8811: =VLOOKUP(M8811,People!$A$1:$C$5,2,0) -> Chuck Magee | O8811: OFF-LA-10001404 | P8811: Office Supplies | Q8811: Labels | R8811: Avery 517 | S8811: 14.76 | T8811: 5 | U8811: 0.2 | V8811: 4.9815
A8812: 8811 | B8812: CA-2019-120614 | C8812: 43615 | D8812: 43620 | E8812: Standard Class | F8812: SM-20950 | G8812: Suzanne McNair | H8812: Corporate | I8812: United States | J8812: Los Angeles | K8812: California | L8812: 90004 | M8812: West | N8812: =VLOOKUP(M8812,People!$A$1:$C$5,2,0) -> Anna Andreadi | O8812: OFF-PA-10004911 | P8812: Office Supplies | Q8812: Paper | R8812: Rediform S.O.S. 1-Up Phone Message Bk, 4-1/4x3-1/16 Bk, 1 Form/Pg, 40 Messages/Bk, 3/Pk | S8812: 37.52 | T8812: 4 | U8812: 0 | V8812: 18.0096
... A9147: 9146 | B9147: CA-2017-126970 | C9147: 42998 | D9147: 43002 | E9147: Standard Class | F9147: TP-21130 | G9147: Theone Pippenger | H9147: Consumer | I9147: United States | J9147: Naperville | K9147: Illinois | L9147: 60540 | M9147: Central | N9147: =VLOOKUP(M9147,People!$A$1:$C$5,2,0) -> Kelly Williams | O9147: OFF-BI-10000138 | P9147: Office Supplies | Q9147: Binders | R9147: Acco Translucent Poly Ring Binders | S9147: 2.808 | T9147: 3 | U9147: 0.8 | V9147: -4.4928
A9148: 9147 | B9148: US-2018-165505 | C9148: 43123 | D9148: 43127 | E9148: Standard Class | F9148: CB-12535 | G9148: Claudia Bergmann | H9148: Corporate | I9148: United States | J9148: Burlington | K9148: Vermont | M9148: East | N9148: =VLOOKUP(M9148,People!$A$1:$C$5,2,0) -> Chuck Magee | O9148: TEC-AC-10002926 | P9148: Technology | Q9148: Accessories | R9148: Logitech Wireless Marathon Mouse M705 | S9148: 99.98 | T9148: 2 | U9148: 0 | V9148: 42.9914
A9149: 9148 | B9149: US-2018-165505 | C9149: 43123 | D9149: 43127 | E9149: Standard Class | F9149: CB-12535 | G9149: Claudia Bergmann | H9149: Corporate | I9149: United States | J9149: Burlington | K9149: Vermont | M9149: East | N9149: =VLOOKUP(M9149,People!$A$1:$C$5,2,0) -> Chuck Magee | O9149: OFF-AR-10003477 | P9149: Office Supplies | Q9149: Art | R9149: 4009 Highlighters | S9149: 8.04 | T9149: 6 | U9149: 0 | V9149: 2.7336
A9150: 9149 | B9150: US-2018-165505 | C9150: 43123 | D9150: 43127 | E9150: Standard Class | F9150: CB-12535 | G9150: Claudia Bergmann | H9150: Corporate | I9150: United States | J9150: Burlington | K9150: Vermont | M9150: East | N9150: =VLOOKUP(M9150,People!$A$1:$C$5,2,0) -> Chuck Magee | O9150: OFF-ST-10001526 | P9150: Office Supplies | Q9150: Storage | R9150: Iceberg Mobile Mega Data/Printer Cart | S9150: 1564.29 | T9150: 13 | U9150: 0 | V9150: 406.7154
A9151: 9150 | B9151: US-2016-157070 | C9151: 42522 | D9151: 42527 | E9151: Standard Class | F9151: QJ-19255 | G9151: Quincy Jones | H9151: Corporate | I9151: United States | J9151: Detroit | K9151: Michigan | L9151: 48234 | M9151: Central | N9151: =VLOOKUP(M9151,People!$A$1:$C$5,2,0) -> Kelly Williams | O9151: OFF-BI-10001765 | P9151: Office Supplies | Q9151: Binders | R9151: Wilson Jones Heavy-Duty Casebound Ring Binders with Metal Hinges | S9151: 138.56 | T9151: 4 | U9151: 0 | V9151: 66.5088
A9152: 9151 | B9152: US-2016-157070 | C9152: 42522 | D9152: 42527 | E9152: Standard Class | F9152: QJ-19255 | G9152: Quincy Jones | H9152: Corporate | I9152: United States | J9152: Detroit | K9152: Michigan | L9152: 48234 | M9152: Central | N9152: =VLOOKUP(M9152,People!$A$1:$C$5,2,0) -> Kelly Williams | O9152: OFF-AP-10004859 | P9152: Office Supplies | Q9152: Appliances | R9152: Acco 6 Outlet Guardian Premium Surge Suppressor | S9152: 65.52 | T9152: 5 | U9152: 0.1 | V9152: 12.376
A9153: 9152 | B9153: US-2017-106873 | C9153: 43002 | D9153: 43007 | E9153: Second Class | F9153: KM-16720 | G9153: Kunst Miller | H9153: Consumer | I9153: United States | J9153: Avondale | K9153: Arizona | L9153: 85323 | M9153: West | N9153: =VLOOKUP(M9153,People!$A$1:$C$5,2,0) -> Anna Andreadi | O9153: OFF-AR-10003179 | P9153: Office Supplies | Q9153: Art | R9153: Dixon Ticonderoga Core-Lock Colored Pencils | S9153: 14.576 | T9153: 2 | U9153: 0.2 | V9153: 2.3686
A9154: 9153 | B9154: US-2017-106873 | C9154: 43002 | D9154: 43007 | E9154: Second Class | F9154: KM-16720 | G9154: Kunst Miller | H9154: Consumer | I9154: United States | J9154: Avondale | K9154: Arizona | L9154: 85323 | M9154: West | N9154: =VLOOKUP(M9154,People!$A$1:$C$5,2,0) -> Anna Andreadi | O9154: TEC-AC-10002345 | P9154: Technology | Q9154: Accessories | R9154: HP Standard 104 key PS/2 Keyboard | S9154: 23.2 | T9154: 2 | U9154: 0.2 | V9154: 1.45
A9155: 9154 | B9155: US-2017-106873 | C9155: 43002 | D9155: 43007 | E9155: Second Class | F9155: KM-16720 | G9155: Kunst Miller | H9155: Consumer | I9155: United States | J9155: Avondale | K9155: Arizona | L9155: 85323 | M9155: West | N9155: =VLOOKUP(M9155,People!$A$1:$C$5,2,0) -> Anna Andreadi | O9155: OFF-AR-10001246 | P9155: Office Supplies | Q9155: Art | R9155: Newell 317 | S9155: 16.464 | T9155: 7 | U9155: 0.2 | V9155: 1.8522
A9156: 9155 | B9156: CA-2018-132990 | C9156: 43313 | D9156: 43315 | E9156: Second Class | F9156: KM-16660 | G9156: Khloe Miller | H9156: Consumer | I9156: United States | J9156: Philadelphia | K9156: Pennsylvania | L9156: 19140 | M9156: East | N9156: =VLOOKUP(M9156,People!$A$1:$C$5,2,0) -> Chuck Magee | O9156: FUR-FU-10004864 | P9156: Furniture | Q9156: Furnishings | R9156: Eldon 500 Class Desk Accessories | S9156: 19.312 | T9156: 2 | U9156: 0.2 | V9156: 3.1382
A9157: 9156 | B9157: CA-2016-102645 | C9157: 42392 | D9157: 42397 | E9157: Standard Class | F9157: IM-15055 | G9157: Ionia McGrath | H9157: Consumer | I9157: United States | J9157: Las Vegas | K9157: Nevada | L9157: 89115 | M9157: West | N9157: =VLOOKUP(M9157,People!$A$1:$C$5,2,0) -> Anna Andreadi | O9157: OFF-PA-10001804 | P9157: Office Supplies | Q9157: Paper | R9157: Xerox 195 | S9157: 40.08 | T9157: 6 | U9157: 0 | V9157: 19.2384
A9158: 9157 | B9158: CA-2016-134215 | C9158: 42586 | D9158: 42590 | E9158: Standard Class | F9158: ML-17395 | G9158: Marina Lichtenstein | H9158: Corporate | I9158: United States | J9158: Bangor | K9158: Maine | L9158: 4401 | M9158: East | N9158: =VLOOKUP(M9158,People!$A$1:$C$5,2,0) -> Chuck Magee | O9158: OFF-AP-10001271 | P9158: Office Supplies | Q9158: Appliances | R9158: Eureka The Boss Cordless Rechargeable Stick Vac | S9158: 101.96 | T9158: 2 | U9158: 0 | V9158: 27.5292
A9159: 9158 | B9159: CA-2016-134215 | C9159: 42586 | D9159: 42590 | E9159: Standard Class | F9159: ML-17395 | G9159: Marina Lichtenstein | H9159: Corporate | I9159: United States | J9159: Bangor | K9159: Maine | L9159: 4401 | M9159: East | N9159: =VLOOKUP(M9159,People!$A$1:$C$5,2,0) -> Chuck Magee | O9159: OFF-PA-10004353 | P9159: Office Supplies | Q9159: Paper | R9159: Southworth 25% Cotton Premium Laser Paper and Envelopes | S9159: 259.74 | T9159: 13 | U9159: 0 | V9159: 124.6752
A9160: 9159 | B9160: CA-2016-134215 | C9160: 42586 | D9160: 42590 | E9160: Standard Class | F9160: ML-17395 | G9160: Marina Lichtenstein | H9160: Corporate | I9160: United States | J9160: Bangor | K9160: Maine | L9160: 4401 | M9160: East | N9160: =VLOOKUP(M9160,People!$A$1:$C$5,2,0) -> Chuck Magee | O9160: TEC-AC-10002473 | P9160: Technology | Q9160: Accessories | R9160: Maxell 4.7GB DVD-R | S9160: 255.42 | T9160: 9 | U9160: 0 | V9160: 104.7222
A9161: 9160 | B9161: CA-2018-118934 | C9161: 43321 | D9161: 43326 | E9161: Standard Class | F9161: GH-14410 | G9161: Gary Hansen | H9161: Home Office | I9161: United States | J9161: Hendersonville | K9161: Tennessee | L9161: 37075 | M9161: South | N9161: =VLOOKUP(M9161,People!$A$1:$C$5,2,0) -> Cassandra Brandow | O9161: OFF-BI-10003314 | P9161: Office Supplies | Q9161: Binders | R9161: Tuff Stuff Recycled Round Ring Binders | S9161: 4.338 | T9161: 3 | U9161: 0.7 | V9161: -3.0366
A9162: 9161 | B9162: CA-2018-118934 | C9162: 43321 | D9162: 43326 | E9162: Standard Class | F9162: GH-14410 | G9162: Gary Hansen | H9162: Home Office | I9162: United States | J9162: Hendersonville | K9162: Tennessee | L9162: 37075 | M9162: South | N9162: =VLOOKUP(M9162,People!$A$1:$C$5,2,0) -> Cassandra Brandow | O9162: OFF-BI-10004465 | P9162: Office Supplies | Q9162: Binders | R9162: Avery Durable Slant Ring Binders | S9162: 11.88 | T9162: 5 | U9162: 0.7 | V9162: -7.92
... A9387: 9386 | B9387: CA-2019-163097 | C9387: 43704 | D9387: 43708 | E9387: Standard Class | F9387: SF-20200 | G9387: Sarah Foster | H9387: Consumer | I9387: United States | J9387: Mesa | K9387: Arizona | L9387: 85204 | M9387: West | N9387: =VLOOKUP(M9387,People!$A$1:$C$5,2,0) -> Anna Andreadi | O9387: FUR-FU-10004973 | P9387: Furniture | Q9387: Furnishings | R9387: Flat Face Poster Frame | S9387: 120.576 | T9387: 8 | U9387: 0.2 | V9387: 33.1584
A9388: 9387 | B9388: US-2019-127292 | C9388: 43484 | D9388: 43488 | E9388: Standard Class | F9388: RM-19375 | G9388: Raymond Messe | H9388: Consumer | I9388: United States | J9388: Burlington | K9388: Vermont | M9388: East | N9388: =VLOOKUP(M9388,People!$A$1:$C$5,2,0) -> Chuck Magee | O9388: OFF-PA-10000157 | P9388: Office Supplies | Q9388: Paper | R9388: Xerox 191 | S9388: 79.92 | T9388: 4 | U9388: 0 | V9388: 37.5624
A9389: 9388 | B9389: US-2019-127292 | C9389: 43484 | D9389: 43488 | E9389: Standard Class | F9389: RM-19375 | G9389: Raymond Messe | H9389: Consumer | I9389: United States | J9389: Burlington | K9389: Vermont | M9389: East | N9389: =VLOOKUP(M9389,People!$A$1:$C$5,2,0) -> Chuck Magee | O9389: OFF-PA-10001970 | P9389: Office Supplies | Q9389: Paper | R9389: Xerox 1881 | S9389: 12.28 | T9389: 1 | U9389: 0 | V9389: 5.7716
A9390: 9389 | B9390: US-2019-127292 | C9390: 43484 | D9390: 43488 | E9390: Standard Class | F9390: RM-19375 | G9390: Raymond Messe | H9390: Consumer | I9390: United States | J9390: Burlington | K9390: Vermont | M9390: East | N9390: =VLOOKUP(M9390,People!$A$1:$C$5,2,0) -> Chuck Magee | O9390: OFF-AP-10000828 | P9390: Office Supplies | Q9390: Appliances | R9390: Avanti 4.4 Cu. Ft. Refrigerator | S9390: 542.94 | T9390: 3 | U9390: 0 | V9390: 152.0232
A9391: 9390 | B9391: US-2019-127292 | C9391: 43484 | D9391: 43488 | E9391: Standard Class | F9391: RM-19375 | G9391: Raymond Messe | H9391: Consumer | I9391: United States | J9391: Burlington | K9391: Vermont | M9391: East | N9391: =VLOOKUP(M9391,People!$A$1:$C$5,2,0) -> Chuck Magee | O9391: OFF-EN-10001509 | P9391: Office Supplies | Q9391: Envelopes | R9391: Poly String Tie Envelopes | S9391: 2.04 | T9391: 1 | U9391: 0 | V9391: 0.9588
A9392: 9391 | B9392: CA-2017-163734 | C9392: 42905 | D9392: 42910 | E9392: Standard Class | F9392: KM-16375 | G9392: Katherine Murray | H9392: Home Office | I9392: United States | J9392: Houston | K9392: Texas | L9392: 77070 | M9392: Central | N9392: =VLOOKUP(M9392,People!$A$1:$C$5,2,0) -> Kelly Williams | O9392: OFF-ST-10003692 | P9392: Office Supplies | Q9392: Storage | R9392: Recycled Steel Personal File for Hanging File Folders | S9392: 228.92 | T9392: 5 | U9392: 0.2 | V9392: 14.3075
A9393: 9392 | B9393: CA-2019-162474 | C9393: 43537 | D9393: 43540 | E9393: First Class | F9393: FH-14275 | G9393: Frank Hawley | H9393: Corporate | I9393: United States | J9393: Aurora | K9393: Illinois | L9393: 60505 | M9393: Central | N9393: =VLOOKUP(M9393,People!$A$1:$C$5,2,0) -> Kelly Williams | O9393: TEC-PH-10004700 | P9393: Technology | Q9393: Phones | R9393: PowerGen Dual USB Car Charger | S9393: 7.992 | T9393: 1 | U9393: 0.2 | V9393: 2.5974
A9394: 9393 | B9394: CA-2017-130848 | C9394: 43033 | D9394: 43033 | E9394: Same Day | F9394: DG-13300 | G9394: Deirdre Greer | H9394: Corporate | I9394: United States | J9394: Denver | K9394: Colorado | L9394: 80219 | M9394: West | N9394: =VLOOKUP(M9394,People!$A$1:$C$5,2,0) -> Anna Andreadi | O9394: FUR-CH-10000422 | P9394: Furniture | Q9394: Chairs | R9394: Global Highback Leather Tilter in Burgundy | S9394: 582.336 | T9394: 8 | U9394: 0.2 | V9394: -29.1168
A9395: 9394 | B9395: CA-2016-125997 | C9395: 42633 | D9395: 42636 | E9395: First Class | F9395: MW-18220 | G9395: Mitch Webber | H9395: Consumer | I9395: United States | J9395: New York City | K9395: New York | L9395: 10011 | M9395: East | N9395: =VLOOKUP(M9395,People!$A$1:$C$5,2,0) -> Chuck Magee | O9395: TEC-PH-10003484 | P9395: Technology | Q9395: Phones | R9395: Ooma Telo VoIP Home Phone System | S9395: 629.95 | T9395: 5 | U9395: 0 | V9395: 157.4875
A9396: 9395 | B9396: CA-2016-125997 | C9396: 42633 | D9396: 42636 | E9396: First Class | F9396: MW-18220 | G9396: Mitch Webber | H9396: Consumer | I9396: United States | J9396: New York City | K9396: New York | L9396: 10011 | M9396: East | N9396: =VLOOKUP(M9396,People!$A$1:$C$5,2,0) -> Chuck Magee | O9396: FUR-CH-10001394 | P9396: Furniture | Q9396: Chairs | R9396: Global Leather Executive Chair | S9396: 631.782 | T9396: 2 | U9396: 0.1 | V9396: 140.396
A9397: 9396 | B9397: CA-2016-125997 | C9397: 42633 | D9397: 42636 | E9397: First Class | F9397: MW-18220 | G9397: Mitch Webber | H9397: Consumer | I9397: United States | J9397: New York City | K9397: New York | L9397: 10011 | M9397: East | N9397: =VLOOKUP(M9397,People!$A$1:$C$5,2,0) -> Chuck Magee | O9397: FUR-BO-10002213 | P9397: Furniture | Q9397: Bookcases | R9397: DMI Eclipse Executive Suite Bookcases | S9397: 801.568 | T9397: 2 | U9397: 0.2 | V9397: -10.0196
A9398: 9397 | B9398: CA-2016-125997 | C9398: 42633 | D9398: 42636 | E9398: First Class | F9398: MW-18220 | G9398: Mitch Webber | H9398: Consumer | I9398: United States | J9398: New York City | K9398: New York | L9398: 10011 | M9398: East | N9398: =VLOOKUP(M9398,People!$A$1:$C$5,2,0) -> Chuck Magee | O9398: OFF-LA-10002762 | P9398: Office Supplies | Q9398: Labels | R9398: Avery 485 | S9398: 75.18 | T9398: 6 | U9398: 0 | V9398: 35.3346
A9399: 9398 | B9399: CA-2016-125997 | C9399: 42633 | D9399: 42636 | E9399: First Class | F9399: MW-18220 | G9399: Mitch Webber | H9399: Consumer | I9399: United States | J9399: New York City | K9399: New York | L9399: 10011 | M9399: East | N9399: =VLOOKUP(M9399,People!$A$1:$C$5,2,0) -> Chuck Magee | O9399: OFF-AP-10003842 | P9399: Office Supplies | Q9399: Appliances | R9399: Euro-Pro Shark Turbo Vacuum | S9399: 30.98 | T9399: 1 | U9399: 0 | V9399: 8.0548
A9400: 9399 | B9400: CA-2016-125997 | C9400: 42633 | D9400: 42636 | E9400: First Class | F9400: MW-18220 | G9400: Mitch Webber | H9400: Consumer | I9400: United States | J9400: New York City | K9400: New York | L9400: 10011 | M9400: East | N9400: =VLOOKUP(M9400,People!$A$1:$C$5,2,0) -> Chuck Magee | O9400: TEC-PH-10003072 | P9400: Technology | Q9400: Phones | R9400: Panasonic KX-TG9541B DECT 6.0 Digital 2-Line Expandable Cordless Phone With Digital Answering System | S9400: 1349.91 | T9400: 9 | U9400: 0 | V9400: 661.4559
A9401: 9400 | B9401: CA-2018-103128 | C9401: 43415 | D9401: 43419 | E9401: Standard Class | F9401: SC-20845 | G9401: Sung Chung | H9401: Consumer | I9401: United States | J9401: Arlington Heights | K9401: Illinois | L9401: 60004 | M9401: Central | N9401: =VLOOKUP(M9401,People!$A$1:$C$5,2,0) -> Kelly Williams | O9401: OFF-AR-10003394 | P9401: Office Supplies | Q9401: Art | R9401: Newell 332 | S9401: 14.112 | T9401: 6 | U9401: 0.2 | V9401: 1.2348
A9402: 9401 | B9402: CA-2017-167696 | C9402: 42994 | D9402: 42999 | E9402: Standard Class | F9402: BD-11500 | G9402: Bradley Drucker | H9402: Consumer | I9402: United States | J9402: Newport News | K9402: Virginia | L9402: 23602 | M9402: South | N9402: =VLOOKUP(M9402,People!$A$1:$C$5,2,0) -> Cassandra Brandow | O9402: OFF-EN-10001539 | P9402: Office Supplies | Q9402: Envelopes | R9402: Staple envelope | S9402: 31.12 | T9402: 4 | U9402: 0 | V9402: 14.6264
A9403: 9402 | B9403: CA-2016-159814 | C9403: 42545 | D9403: 42549 | E9403: Standard Class | F9403: LP-17080 | G9403: Liz Pelletier | H9403: Consumer | I9403: United States | J9403: Tucson | K9403: Arizona | L9403: 85705 | M9403: West | N9403: =VLOOKUP(M9403,People!$A$1:$C$5,2,0) -> Anna Andreadi | O9403: FUR-FU-10001731 | P9403: Furniture | Q9403: Furnishings | R9403: Acrylic Self-Standing Desk Frames | S9403: 4.272 | T9403: 2 | U9403: 0.2 | V9403: 0.9612
... A9742: 9741 | B9742: CA-2019-129294 | C9742: 43540 | D9742: 43545 | E9742: Standard Class | F9742: KD-16615 | G9742: Ken Dana | H9742: Corporate | I9742: United States | J9742: Los Angeles | K9742: California | L9742: 90032 | M9742: West | N9742: =VLOOKUP(M9742,People!$A$1:$C$5,2,0) -> Anna Andreadi | O9742: OFF-AP-10001154 | P9742: Office Supplies | Q9742: Appliances | R9742: Bionaire Personal Warm Mist Humidifier/Vaporizer | S9742: 140.67 | T9742: 3 | U9742: 0 | V9742: 54.8613
A9743: 9742 | B9743: CA-2017-117086 | C9743: 43047 | D9743: 43051 | E9743: Standard Class | F9743: QJ-19255 | G9743: Quincy Jones | H9743: Corporate | I9743: United States | J9743: Burlington | K9743: Vermont | M9743: East | N9743: =VLOOKUP(M9743,People!$A$1:$C$5,2,0) -> Chuck Magee | O9743: FUR-BO-10004834 | P9743: Furniture | Q9743: Bookcases | R9743: Riverside Palais Royal Lawyers Bookcase, Royale Cherry Finish | S9743: 4404.9 | T9743: 5 | U9743: 0 | V9743: 1013.127
A9744: 9743 | B9744: CA-2019-131303 | C9744: 43797 | D9744: 43801 | E9744: Standard Class | F9744: EP-13915 | G9744: Emily Phan | H9744: Consumer | I9744: United States | J9744: San Diego | K9744: California | L9744: 92037 | M9744: West | N9744: =VLOOKUP(M9744,People!$A$1:$C$5,2,0) -> Anna Andreadi | O9744: OFF-LA-10001074 | P9744: Office Supplies | Q9744: Labels | R9744: Round Specialty Laser Printer Labels | S9744: 62.65 | T9744: 5 | U9744: 0 | V9744: 29.4455
A9745: 9744 | B9745: CA-2018-137127 | C9745: 43267 | D9745: 43273 | E9745: Standard Class | F9745: JJ-15445 | G9745: Jennifer Jackson | H9745: Consumer | I9745: United States | J9745: Newark | K9745: Delaware | L9745: 19711 | M9745: East | N9745: =VLOOKUP(M9745,People!$A$1:$C$5,2,0) -> Chuck Magee | O9745: OFF-LA-10001641 | P9745: Office Supplies | Q9745: Labels | R9745: Avery 518 | S9745: 9.45 | T9745: 3 | U9745: 0 | V9745: 4.536
A9746: 9745 | B9746: CA-2019-141782 | C9746: 43486 | D9746: 43490 | E9746: Standard Class | F9746: BE-11410 | G9746: Bobby Elias | H9746: Consumer | I9746: United States | J9746: Aurora | K9746: Illinois | L9746: 60505 | M9746: Central | N9746: =VLOOKUP(M9746,People!$A$1:$C$5,2,0) -> Kelly Williams | O9746: OFF-EN-10002230 | P9746: Office Supplies | Q9746: Envelopes | R9746: Airmail Envelopes | S9746: 268.576 | T9746: 4 | U9746: 0.2 | V9746: 90.6444
A9747: 9746 | B9747: CA-2019-137505 | C9747: 43793 | D9747: 43793 | E9747: Same Day | F9747: BP-11290 | G9747: Beth Paige | H9747: Consumer | I9747: United States | J9747: Los Angeles | K9747: California | L9747: 90008 | M9747: West | N9747: =VLOOKUP(M9747,People!$A$1:$C$5,2,0) -> Anna Andreadi | O9747: FUR-TA-10000617 | P9747: Furniture | Q9747: Tables | R9747: Hon Practical Foundations 30 x 60 Training Table, Light Gray/Charcoal | S9747: 364.08 | T9747: 2 | U9747: 0.2 | V9747: 9.102
A9748: 9747 | B9748: CA-2019-137505 | C9748: 43793 | D9748: 43793 | E9748: Same Day | F9748: BP-11290 | G9748: Beth Paige | H9748: Consumer | I9748: United States | J9748: Los Angeles | K9748: California | L9748: 90008 | M9748: West | N9748: =VLOOKUP(M9748,People!$A$1:$C$5,2,0) -> Anna Andreadi | O9748: FUR-TA-10001676 | P9748: Furniture | Q9748: Tables | R9748: Hon 61000 Series Interactive Training Tables | S9748: 71.088 | T9748: 2 | U9748: 0.2 | V9748: -1.7772
A9749: 9748 | B9749: US-2016-140914 | C9749: 42685 | D9749: 42689 | E9749: Standard Class | F9749: BH-11710 | G9749: Brosina Hoffman | H9749: Consumer | I9749: United States | J9749: Chicago | K9749: Illinois | L9749: 60653 | M9749: Central | N9749: =VLOOKUP(M9749,People!$A$1:$C$5,2,0) -> Kelly Williams | O9749: FUR-FU-10000175 | P9749: Furniture | Q9749: Furnishings | R9749: DAX Wood Document Frame. | S9749: 10.984 | T9749: 2 | U9749: 0.6 | V9749: -7.9634
...

Sheet People
A1: Region | B1: Sales Manager
A2: West | B2: Anna Andreadi
A3: East | B3: Chuck Magee
A4: Central | B4: Kelly Williams
A5: South | B5: Cassandra Brandow

Sheet Returns
A1: Returned | B1: Order ID
A2: Yes | B2: CA-2016-100762
A3: Yes | B3: CA-2016-100762
A4: Yes | B4: CA-2016-100762
A5: Yes | B5: CA-2016-100762
A6: Yes | B6: CA-2016-100867
A7: Yes | B7: CA-2016-102652
A8: Yes | B8: CA-2016-102652
A9: Yes | B9: CA-2016-102652
A10: Yes | B10: CA-2016-102652
A11: Yes | B11: CA-2016-103373
A12: Yes | B12: CA-2016-103744
... A801: Yes | B801: US-2019-155999
